keba_keenergy_api/__init__.py
keba_keenergy_api/api.py
keba_keenergy_api/constants.py
keba_keenergy_api/endpoints.py
keba_keenergy_api/error.py
keba_keenergy_api/py.typed
keba_keenergy_api/version.py
keba_keenergy_api-2.6.0.dist-info/licenses/LICENSE
keba_keenergy_api-2.6.0.dist-info/METADATA
keba_keenergy_api-2.6.0.dist-info/WHEEL
keba_keenergy_api-2.6.0.dist-info/top_level.txt
keba_keenergy_api-2.6.0.dist-info/RECORD
