Metadata-Version: 2.4
Name: keba_keenergy_api
Version: 2.6.0
Summary: A Python wrapper for the KEBA KeEnergy API.
Author-email: Michael Hacker <mh@superbox.one>
Maintainer-email: Michael Hacker <mh@superbox.one>
Project-URL: Repository, https://github.com/superbox-dev/keba_keenergy_api
Project-URL: Issues, https://github.com/superbox-dev/keba_keenergy_api/issues
Keywords: api,component,custom component,custom integration,keba,keenergy,hacs-component,hacs-integration,hacs-repository,hacs,hass,home assistant,home-assistant,homeassistant,integration
Classifier: Development Status :: 5 - Production/Stable
Classifier: Programming Language :: Python :: 3
Classifier: Programming Language :: Python :: 3.10
Classifier: Programming Language :: Python :: 3.11
Classifier: Programming Language :: Python :: 3.12
Classifier: Programming Language :: Python :: 3.13
Classifier: Programming Language :: Python :: 3 :: Only
Classifier: Operating System :: OS Independent
Classifier: Topic :: Software Development :: Libraries
Classifier: Topic :: Software Development :: Libraries :: Python Modules
Requires-Python: >=3.10
License-File: LICENSE
Requires-Dist: aiohttp==3.*
Dynamic: license-file
